pathpy/__init__.py
pathpy/_version.py
pathpy/cli.py
pathpy/lib.py
pathpy/py.typed
pathpy4-4.0.0.dist-info/LICENSE.txt
pathpy4-4.0.0.dist-info/METADATA
pathpy4-4.0.0.dist-info/WHEEL
pathpy4-4.0.0.dist-info/top_level.txt
pathpy4-4.0.0.dist-info/RECORD
