Metadata-Version: 2.1
Name: pathpy4
Version: 4.0.0
Summary: pathpy: path data analysis
Home-page: https://www.pathpy.net
Author: Ingo Scholtes, Jürgen Hackl
Author-email: info@pathpy.net
Maintainer: Ingo Scholtes, Jürgen Hackl
Maintainer-email: info@pathpy.net
License: AGPL-3.0+
Download-URL: https://github.com/pathpy/pathpy
Project-URL: Issue Tracker, https://github.com/pathpy/pathpy/issues
Project-URL: Documentation, https://pathpy.github.io/
Project-URL: Source Code, https://github.com/pathpy/pathpy
Platform: Linux
Platform: Mac OSX
Platform: Windows
Platform: Unix
Classifier: Development Status :: 2 - Pre-Alpha
Classifier: Intended Audience :: Science/Research
Classifier: Programming Language :: Python :: 3.7
Classifier: Programming Language :: Python :: 3.8
Classifier: License :: OSI Approved :: GNU Affero General Public License v3 or later (AGPLv3+)
Classifier: Topic :: Software Development :: Libraries :: Python Modules
Classifier: Topic :: Scientific/Engineering :: Artificial Intelligence
Classifier: Topic :: Scientific/Engineering :: Visualization
Classifier: Topic :: Scientific/Engineering :: Bio-Informatics
Classifier: Topic :: Scientific/Engineering :: Information Analysis
Classifier: Topic :: Scientific/Engineering :: Mathematics
Classifier: Topic :: Scientific/Engineering :: Physics
Classifier: Operating System :: OS Independent
Classifier: Programming Language :: Python
Classifier: Programming Language :: Python :: 3
Classifier: Programming Language :: Python :: 3 :: Only
Classifier: Programming Language :: Python :: 3.8
Classifier: Programming Language :: Python :: 3.9
Classifier: Programming Language :: Python :: 3.10
Requires-Python: >=3.8
License-File: LICENSE.txt
Requires-Dist: click (==8.0.3)
Requires-Dist: colorama (==0.4.4)
Requires-Dist: typer (==0.4.0)
